decaychain/BatemanDecay.py
decaychain/BatemanMulti.py
decaychain/DataLoader.py
decaychain/DecayCalculation.py
decaychain/DecayChain.py
decaychain/FormatInput.py
decaychain/HalfLifeSearch.py
decaychain/MeasurementUnit.py
decaychain/Nuclide.py
decaychain/NuclideFormatter.py
decaychain/__init__.py
decaychain/data/ICRP-07.NDX
decaychain/data/__init__.py
decaychain-0.7.1.dist-info/LICENSE
decaychain-0.7.1.dist-info/METADATA
decaychain-0.7.1.dist-info/WHEEL
decaychain-0.7.1.dist-info/top_level.txt
decaychain-0.7.1.dist-info/RECORD
