Metadata-Version: 2.1
Name: decaychain
Version: 0.7.1
Summary: Module to radioactively decay radioactive elements using the ICRP-107 and Bateman Equation
Home-page: https://github.com/Rolleroo/decaychain
Author: Kenneth McKee
Author-email: kenneth.mckee@protonmail.com
License: MIT
Platform: UNKNOWN
Classifier: Programming Language :: Python :: 3.6
Classifier: Programming Language :: Python :: 3.7
Classifier: License :: OSI Approved :: MIT License
Classifier: Operating System :: POSIX :: Linux
Classifier: Development Status :: 3 - Alpha
Classifier: Intended Audience :: Science/Research
Classifier: Intended Audience :: Education
Classifier: Topic :: Scientific/Engineering
Classifier: Topic :: Education 
Requires-Python: >=3.6
Requires-Dist: batemaneq (>=0.2.2)
Requires-Dist: Pint (>=0.12)
Requires-Dist: importlib-resources ; python_version < "3.7"
